SCTW_DS/NeuralNet/__init__.py
SCTW_DS/NeuralNet/binaries/NeuralNetwork.cpython-312-darwin.so
SCTW_DS/Regression/__init__.py
SCTW_DS/Utils/__init__.py
SCTW_DS/scripts/__init__.py
SCTW_DS/scripts/Regression/__init__.py
SCTW_DS/scripts/Regression/LinearRegression/LinearRegression.py
SCTW_DS/scripts/Regression/LinearRegression/MultiVariateLinearRegression.py
SCTW_DS/scripts/Regression/PolynomialRegression/PolynomialRegression.py
SCTW_DS/scripts/Utils/__init__.py
SCTW_DS/scripts/Utils/dataCleaner.py
SCTW_DS/scripts/Utils/generateDataset.py
SCTW_DS/scripts/Utils/progress_bar.py
SCTW_DS/scripts/Utils/trainTestSplit.py
SCTW_DS-0.3.3.dist-info/METADATA
SCTW_DS-0.3.3.dist-info/WHEEL
SCTW_DS-0.3.3.dist-info/top_level.txt
SCTW_DS-0.3.3.dist-info/RECORD
