Metadata-Version: 2.1
Name: SCTW_DS
Version: 0.3.3
Summary: A python library for implementation of some Data Science topics.
Home-page: https://github.com/dmeirLemas/DataScience
Author: dmeirLemas
Author-email: dmeirLemas@gmail.com
Classifier: Development Status :: 3 - Alpha
Classifier: Intended Audience :: Developers
Classifier: License :: OSI Approved :: MIT License
Classifier: Programming Language :: Python :: 3
Classifier: Programming Language :: Python :: 3.8
Classifier: Programming Language :: Python :: 3.9
Classifier: Programming Language :: Python :: 3.10
Requires-Python: >=3.8
